{
  "name": "65_womack_random_acts",
  "category": "persona_gaits",
  "type": "synapse",
  "architecture": "crosswired_10",
  "weights": {
    "w03": -0.8,
    "w13": 0,
    "w23": 0,
    "w04": 0,
    "w14": 0,
    "w24": 0.8,
    "w34": 0,
    "w43": 0,
    "w33": 0.5,
    "w44": -0.5
  },
  "SIM_STEPS": 4000,
  "MAX_FORCE": 150.0,
  "DT": 0.004167,
  "GRAVITY_Z": -9.8,
  "ROBOT_FRICTION": 2.5,
  "dx": -11.56,
  "dy": 4.18,
  "true_distance": 12.29,
  "heading": 160.1,
  "yaw_degrees": -23.6,
  "max_tilt": 10,
  "description": "Random Acts of Senseless Violence: only 2 sensor synapses (w03, w24) + self-feedback (w33=0.5, w44=-0.5). Institutional feedback loops drive backward locomotion. Tilt only 10\u00b0 \u2014 the most stable gait in the zoo relative to its displacement. Survival through structural austerity.",
  "telemetry": {
    "stride_freq_hz": 2.47,
    "duty_cycle": 0.618,
    "mean_torque": 62.33,
    "transient_frac": 0.852,
    "mean_speed": 1.016,
    "speed_cv": 0.724,
    "attractor_type": "complex",
    "efficiency": 0.1975,
    "pareto_optimal": false
  }
}
