{
  "name": "84_foucault_madness",
  "category": "persona_gaits",
  "type": "synapse",
  "architecture": "crosswired_10",
  "weights": {
    "w03": -0.3,
    "w13": -0.3,
    "w23": -0.3,
    "w04": 0.3,
    "w14": 0.3,
    "w24": 0.3,
    "w34": 0,
    "w43": 0,
    "w33": 0.9,
    "w44": -0.9
  },
  "SIM_STEPS": 4000,
  "MAX_FORCE": 150.0,
  "DT": 0.004167,
  "GRAVITY_Z": -9.8,
  "ROBOT_FRICTION": 2.5,
  "dx": -14.12,
  "dy": 2.22,
  "true_distance": 14.29,
  "heading": 171.1,
  "yaw_degrees": -14.9,
  "max_tilt": 14,
  "description": "Madness and Civilization: moderate external drive (\u00b10.3) with extreme self-feedback (w33=0.9, w44=-0.9). The confined mind \u2014 trapped in internal loops yet still producing locomotion (14m, tilt 14\u00b0). The institution generates its own logic.",
  "telemetry": {
    "stride_freq_hz": 5.41,
    "duty_cycle": 0.62,
    "mean_torque": 89.94,
    "transient_frac": 0.745,
    "mean_speed": 1.216,
    "speed_cv": 0.466,
    "attractor_type": "limit_cycle",
    "efficiency": 0.1594,
    "pareto_optimal": false
  }
}
